katanalogger/__init__.py
katanalogger/logger.py
katanalogger-0.1.1.dist-info/LICENSE
katanalogger-0.1.1.dist-info/METADATA
katanalogger-0.1.1.dist-info/WHEEL
katanalogger-0.1.1.dist-info/top_level.txt
katanalogger-0.1.1.dist-info/RECORD
