Metadata-Version: 2.2
Name: katanalogger
Version: 0.1.1
Summary: A powerful and flexible logging library for Python.
Author-email: SoulNaturalist <212.rss@mail.ru>
License:                     GNU AFFERO GENERAL PUBLIC LICENSE
Project-URL: Homepage, https://github.com/SoulNaturalist/katanalogger
Project-URL: Repository, https://github.com/SoulNaturalist/katanalogger
Project-URL: Issues, https://github.com/SoulNaturalist/katanalogger/issues
Project-URL: Documentation, https://github.com/SoulNaturalist/katanalogger#readme
Keywords: logging,logger,async,colorama,rich,emoji,performance
Classifier: Development Status :: 4 - Beta
Classifier: Intended Audience :: Developers
Classifier: License :: OSI Approved :: GNU Affero General Public License v3
Classifier: Programming Language :: Python :: 3
Classifier: Programming Language :: Python :: 3.7
Classifier: Programming Language :: Python :: 3.8
Classifier: Programming Language :: Python :: 3.9
Classifier: Programming Language :: Python :: 3.10
Classifier: Programming Language :: Python :: 3.11
Classifier: Operating System :: OS Independent
Classifier: Topic :: Software Development :: Libraries :: Python Modules
Classifier: Topic :: System :: Logging
Requires-Python: >=3.7
License-File: LICENSE
Requires-Dist: colorama>=0.4.6
Requires-Dist: rich>=13.0.0
